Mold2_pywrapper/__init__.py
Mold2_pywrapper/descriptors.json
Mold2_pywrapper/mold2_wrapper.py
Mold2_pywrapper-0.1.2.dist-info/LICENSE
Mold2_pywrapper-0.1.2.dist-info/METADATA
Mold2_pywrapper-0.1.2.dist-info/WHEEL
Mold2_pywrapper-0.1.2.dist-info/top_level.txt
Mold2_pywrapper-0.1.2.dist-info/RECORD
