Metadata-Version: 2.1
Name: Mold2_pywrapper
Version: 0.1.2
Summary: Python wrapper for Mold2 descriptors
Home-page: https://github.com/OlivierBeq/Mold2_pywrapper
Author: Olivier J. M. Béquignon
Author-email: "olivier.bequignon.maintainer@gmail.com"
Maintainer: Olivier J. M. Béquignon
Maintainer-email: "olivier.bequignon.maintainer@gmail.com"
Keywords: mold2,molecular descriptors,cheminformatics,toxicoinformatics,QSAR
Classifier: Development Status :: 5 - Production/Stable
Classifier: License :: OSI Approved :: MIT License
Classifier: Programming Language :: Python :: 3.10
Classifier: Programming Language :: Python :: 3.9
Classifier: Programming Language :: Python :: 3.8
Classifier: Programming Language :: Python :: 3.7
Classifier: Programming Language :: Python :: 3.6
License-File: LICENSE
Requires-Dist: more-itertools
Requires-Dist: pandas
Requires-Dist: rdkit
Requires-Dist: requests
Requires-Dist: pystow
Requires-Dist: bounded-pool-executor
Requires-Dist: numpy>=2.0.0
Provides-Extra: docs
Requires-Dist: sphinx; extra == "docs"
Requires-Dist: sphinx-rtd-theme; extra == "docs"
Requires-Dist: sphinx-autodoc-typehints; extra == "docs"
Provides-Extra: testing
Requires-Dist: pytest; extra == "testing"
